{
  "title": "4.18.3.1.1  dem:ReliefFeature",
  "path": "/plateaudocument/toc4/toc4_18/toc4_18_03/toc4_18_03_01/_demrelieffeature",
  "content": [
    {
      "type": "title",
      "content": {
        "content": [
          {
            "text": "4.18.3.1.1\tdem:ReliefFeature",
            "type": "text"
          }
        ],
        "type": "title"
      }
    },
    {
      "type": "tableFigure",
      "content": {
        "attrs": {
          "resourceID": "urn:metanorma:doc-part:_5441ec11-2ee3-8d9d-4eda-fde3b27cc7a5"
        },
        "content": [
          {
            "content": [
              {
                "content": [
                  {
                    "text": "表",
                    "type": "text"
                  }
                ],
                "type": "span"
              },
              {
                "text": "4-776",
                "type": "text"
              }
            ],
            "type": "figCaption"
          },
          {
            "attrs": {
              "colWidths": [
                "25%",
                "25%",
                "50%"
              ]
            },
            "content": [
              {
                "content": [
                  {
                    "attrs": {
                      "background": null,
                      "colspan": null,
                      "colwidth": null,
                      "rowspan": null
                    },
                    "content": [
                      {
                        "attrs": {
                          "resourceID": ""
                        },
                        "content": [
                          {
                            "text": "型の定義",
                            "type": "text"
                          }
                        ],
                        "type": "paragraph"
                      }
                    ],
                    "type": "table_header"
                  },
                  {
                    "attrs": {
                      "background": null,
                      "colspan": "2",
                      "colwidth": null,
                      "rowspan": null
                    },
                    "content": [
                      {
                        "attrs": {
                          "resourceID": "urn:metanorma:doc-part:_4de8781d-8b13-e798-ebfb-7d1d31e27210"
                        },
                        "content": [
                          {
                            "text": "地形の凹凸を表現した地物。",
                            "type": "text"
                          },
                          {
                            "type": "linebreak"
                          },
                          {
                            "text": "基準地域メッシュ（第三次地域区画、一辺の長さ約1km）を地物の単位とする（基準地域メッシュの境界で区切る）。",
                            "type": "text"
                          }
                        ],
                        "type": "paragraph"
                      }
                    ],
                    "type": "table_cell"
                  }
                ],
                "type": "table_row"
              },
              {
                "content": [
                  {
                    "attrs": {
                      "background": null,
                      "colspan": null,
                      "colwidth": null,
                      "rowspan": null
                    },
                    "content": [
                      {
                        "attrs": {
                          "resourceID": ""
                        },
                        "content": [
                          {
                            "text": "上位の型",
                            "type": "text"
                          }
                        ],
                        "type": "paragraph"
                      }
                    ],
                    "type": "table_header"
                  },
                  {
                    "attrs": {
                      "background": null,
                      "colspan": "2",
                      "colwidth": null,
                      "rowspan": null
                    },
                    "content": [
                      {
                        "attrs": {
                          "resourceID": "urn:metanorma:doc-part:_641e889d-cf28-4e9e-a914-c838f18b8905"
                        },
                        "content": [
                          {
                            "text": "core:_CityObject",
                            "type": "text"
                          }
                        ],
                        "type": "paragraph"
                      }
                    ],
                    "type": "table_cell"
                  }
                ],
                "type": "table_row"
              },
              {
                "content": [
                  {
                    "attrs": {
                      "background": null,
                      "colspan": null,
                      "colwidth": null,
                      "rowspan": null
                    },
                    "content": [
                      {
                        "attrs": {
                          "resourceID": ""
                        },
                        "content": [
                          {
                            "text": "ステレオタイプ",
                            "type": "text"
                          }
                        ],
                        "type": "paragraph"
                      }
                    ],
                    "type": "table_header"
                  },
                  {
                    "attrs": {
                      "background": null,
                      "colspan": "2",
                      "colwidth": null,
                      "rowspan": null
                    },
                    "content": [
                      {
                        "attrs": {
                          "resourceID": "urn:metanorma:doc-part:_176aa8f7-54b5-0881-4687-4e2391134b36"
                        },
                        "content": [
                          {
                            "text": "\u003c\u003c FeatureType \u003e\u003e",
                            "type": "text"
                          }
                        ],
                        "type": "paragraph"
                      }
                    ],
                    "type": "table_cell"
                  }
                ],
                "type": "table_row"
              },
              {
                "content": [
                  {
                    "attrs": {
                      "background": null,
                      "colspan": "3",
                      "colwidth": null,
                      "rowspan": null
                    },
                    "content": [
                      {
                        "attrs": {
                          "resourceID": ""
                        },
                        "content": [
                          {
                            "text": "継承する属性",
                            "type": "text"
                          }
                        ],
                        "type": "paragraph"
                      }
                    ],
                    "type": "table_header"
                  }
                ],
                "type": "table_row"
              },
              {
                "content": [
                  {
                    "attrs": {
                      "background": null,
                      "colspan": null,
                      "colwidth": null,
                      "rowspan": null
                    },
                    "content": [
                      {
                        "attrs": {
                          "resourceID": ""
                        },
                        "content": [
                          {
                            "text": "属性名",
                            "type": "text"
                          }
                        ],
                        "type": "paragraph"
                      }
                    ],
                    "type": "table_header"
                  },
                  {
                    "attrs": {
                      "background": null,
                      "colspan": null,
                      "colwidth": null,
                      "rowspan": null
                    },
                    "content": [
                      {
                        "attrs": {
                          "resourceID": ""
                        },
                        "content": [
                          {
                            "text": "属性の型及び多重度",
                            "type": "text"
                          }
                        ],
                        "type": "paragraph"
                      }
                    ],
                    "type": "table_header"
                  },
                  {
                    "attrs": {
                      "background": null,
                      "colspan": null,
                      "colwidth": null,
                      "rowspan": null
                    },
                    "content": [
                      {
                        "attrs": {
                          "resourceID": ""
                        },
                        "content": [
                          {
                            "text": "定義",
                            "type": "text"
                          }
                        ],
                        "type": "paragraph"
                      }
                    ],
                    "type": "table_header"
                  }
                ],
                "type": "table_row"
              },
              {
                "content": [
                  {
                    "attrs": {
                      "background": null,
                      "colspan": null,
                      "colwidth": null,
                      "rowspan": null
                    },
                    "content": [
                      {
                        "attrs": {
                          "resourceID": "urn:metanorma:doc-part:_5965891a-d790-4a06-cee2-302e9b16f4f2"
                        },
                        "content": [
                          {
                            "text": "gml:description",
                            "type": "text"
                          },
                          {
                            "type": "linebreak"
                          },
                          {
                            "text": "     [ _Feature ]",
                            "type": "text"
                          }
                        ],
                        "type": "paragraph"
                      }
                    ],
                    "type": "table_cell"
                  },
                  {
                    "attrs": {
                      "background": null,
                      "colspan": null,
                      "colwidth": null,
                      "rowspan": null
                    },
                    "content": [
                      {
                        "attrs": {
                          "resourceID": "urn:metanorma:doc-part:_0e877f06-38e3-70be-476b-3df0bc5909c6"
                        },
                        "content": [
                          {
                            "text": "gml:StringOrRefType [0..1]",
                            "type": "text"
                          }
                        ],
                        "type": "paragraph"
                      }
                    ],
                    "type": "table_cell"
                  },
                  {
                    "attrs": {
                      "background": null,
                      "colspan": null,
                      "colwidth": null,
                      "rowspan": null
                    },
                    "content": [
                      {
                        "attrs": {
                          "resourceID": "urn:metanorma:doc-part:_e0d80d0c-ce7c-df9a-3c5b-216f5e683af7"
                        },
                        "content": [
                          {
                            "text": "都市オブジェクトの概要。",
                            "type": "text"
                          }
                        ],
                        "type": "paragraph"
                      }
                    ],
                    "type": "table_cell"
                  }
                ],
                "type": "table_row"
              },
              {
                "content": [
                  {
                    "attrs": {
                      "background": null,
                      "colspan": null,
                      "colwidth": null,
                      "rowspan": null
                    },
                    "content": [
                      {
                        "attrs": {
                          "resourceID": "urn:metanorma:doc-part:_05715a10-420d-d502-3692-2f5ec2389296"
                        },
                        "content": [
                          {
                            "text": "gml:name",
                            "type": "text"
                          },
                          {
                            "type": "linebreak"
                          },
                          {
                            "text": "     [ _Feature ]",
                            "type": "text"
                          }
                        ],
                        "type": "paragraph"
                      }
                    ],
                    "type": "table_cell"
                  },
                  {
                    "attrs": {
                      "background": null,
                      "colspan": null,
                      "colwidth": null,
                      "rowspan": null
                    },
                    "content": [
                      {
                        "attrs": {
                          "resourceID": "urn:metanorma:doc-part:_e044edb6-c2c1-8b7c-a7eb-84540572e5c2"
                        },
                        "content": [
                          {
                            "text": "gml::CodeType [0..1]",
                            "type": "text"
                          }
                        ],
                        "type": "paragraph"
                      }
                    ],
                    "type": "table_cell"
                  },
                  {
                    "attrs": {
                      "background": null,
                      "colspan": null,
                      "colwidth": null,
                      "rowspan": null
                    },
                    "content": [
                      {
                        "attrs": {
                          "resourceID": "urn:metanorma:doc-part:_6c5802d2-6d6e-e327-2b92-f7c86d9d7a0f"
                        },
                        "content": [
                          {
                            "text": "都市オブジェクトを識別する名称。文字列とする。",
                            "type": "text"
                          }
                        ],
                        "type": "paragraph"
                      }
                    ],
                    "type": "table_cell"
                  }
                ],
                "type": "table_row"
              },
              {
                "content": [
                  {
                    "attrs": {
                      "background": null,
                      "colspan": null,
                      "colwidth": null,
                      "rowspan": null
                    },
                    "content": [
                      {
                        "attrs": {
                          "resourceID": "urn:metanorma:doc-part:_a75188cd-a8e0-270b-4c49-5c449da37013"
                        },
                        "content": [
                          {
                            "text": "gml:boundedBy",
                            "type": "text"
                          },
                          {
                            "type": "linebreak"
                          },
                          {
                            "text": "     [ _Feature ]",
                            "type": "text"
                          }
                        ],
                        "type": "paragraph"
                      }
                    ],
                    "type": "table_cell"
                  },
                  {
                    "attrs": {
                      "background": null,
                      "colspan": null,
                      "colwidth": null,
                      "rowspan": null
                    },
                    "content": [
                      {
                        "attrs": {
                          "resourceID": "urn:metanorma:doc-part:_0a967bdf-dd9a-be8f-dfa6-1276587ba3be"
                        },
                        "content": [
                          {
                            "text": "gml::Envelope [0..1]",
                            "type": "text"
                          }
                        ],
                        "type": "paragraph"
                      }
                    ],
                    "type": "table_cell"
                  },
                  {
                    "attrs": {
                      "background": null,
                      "colspan": null,
                      "colwidth": null,
                      "rowspan": null
                    },
                    "content": [
                      {
                        "attrs": {
                          "resourceID": "urn:metanorma:doc-part:_9b34587f-d7da-cb3b-0c3c-33960e4fb0e1"
                        },
                        "content": [
                          {
                            "text": "都市オブジェクトの範囲及び適用される空間参照系。",
                            "type": "text"
                          },
                          {
                            "type": "linebreak"
                          },
                          {
                            "text": " CityModelの場合のみ必須とする。",
                            "type": "text"
                          }
                        ],
                        "type": "paragraph"
                      }
                    ],
                    "type": "table_cell"
                  }
                ],
                "type": "table_row"
              },
              {
                "content": [
                  {
                    "attrs": {
                      "background": null,
                      "colspan": null,
                      "colwidth": null,
                      "rowspan": null
                    },
                    "content": [
                      {
                        "attrs": {
                          "resourceID": "urn:metanorma:doc-part:_f41ab6e6-5c5c-5f02-560a-9dbfe9f5d305"
                        },
                        "content": [
                          {
                            "text": "core:creationDate",
                            "type": "text"
                          },
                          {
                            "type": "linebreak"
                          },
                          {
                            "text": "     [ _CityObject ]",
                            "type": "text"
                          }
                        ],
                        "type": "paragraph"
                      }
                    ],
                    "type": "table_cell"
                  },
                  {
                    "attrs": {
                      "background": null,
                      "colspan": null,
                      "colwidth": null,
                      "rowspan": null
                    },
                    "content": [
                      {
                        "attrs": {
                          "resourceID": "urn:metanorma:doc-part:_eebd8b21-9911-f346-793f-1e277c726efb"
                        },
                        "content": [
                          {
                            "text": "xs::date [0..1]",
                            "type": "text"
                          }
                        ],
                        "type": "paragraph"
                      }
                    ],
                    "type": "table_cell"
                  },
                  {
                    "attrs": {
                      "background": null,
                      "colspan": null,
                      "colwidth": null,
                      "rowspan": null
                    },
                    "content": [
                      {
                        "attrs": {
                          "resourceID": "urn:metanorma:doc-part:_cc74fdc4-c4aa-8370-13d8-597c334f4550"
                        },
                        "content": [
                          {
                            "text": "データが作成された日。運用上必須とする。",
                            "type": "text"
                          }
                        ],
                        "type": "paragraph"
                      }
                    ],
                    "type": "table_cell"
                  }
                ],
                "type": "table_row"
              },
              {
                "content": [
                  {
                    "attrs": {
                      "background": null,
                      "colspan": null,
                      "colwidth": null,
                      "rowspan": null
                    },
                    "content": [
                      {
                        "attrs": {
                          "resourceID": "urn:metanorma:doc-part:_8bfe5122-4cb6-802d-6317-8311dd126c91"
                        },
                        "content": [
                          {
                            "text": "core:terminationDate",
                            "type": "text"
                          },
                          {
                            "type": "linebreak"
                          },
                          {
                            "text": "     [ _CityObject ]",
                            "type": "text"
                          }
                        ],
                        "type": "paragraph"
                      }
                    ],
                    "type": "table_cell"
                  },
                  {
                    "attrs": {
                      "background": null,
                      "colspan": null,
                      "colwidth": null,
                      "rowspan": null
                    },
                    "content": [
                      {
                        "attrs": {
                          "resourceID": "urn:metanorma:doc-part:_69e2f9fc-a207-32bc-e46e-b27338d672f6"
                        },
                        "content": [
                          {
                            "text": "xs::date [0..1]",
                            "type": "text"
                          }
                        ],
                        "type": "paragraph"
                      }
                    ],
                    "type": "table_cell"
                  },
                  {
                    "attrs": {
                      "background": null,
                      "colspan": null,
                      "colwidth": null,
                      "rowspan": null
                    },
                    "content": [
                      {
                        "attrs": {
                          "resourceID": "urn:metanorma:doc-part:_72ba1326-2fd2-1a8a-ffe9-7c4f3f7743b0"
                        },
                        "content": [
                          {
                            "text": "データが削除された日。",
                            "type": "text"
                          }
                        ],
                        "type": "paragraph"
                      }
                    ],
                    "type": "table_cell"
                  }
                ],
                "type": "table_row"
              },
              {
                "content": [
                  {
                    "attrs": {
                      "background": null,
                      "colspan": null,
                      "colwidth": null,
                      "rowspan": null
                    },
                    "content": [
                      {
                        "attrs": {
                          "resourceID": "urn:metanorma:doc-part:_e73ea54a-d4ee-0230-cf78-9ad85a84685a"
                        },
                        "content": [
                          {
                            "text": "core:relativeToTerrain",
                            "type": "text"
                          },
                          {
                            "type": "linebreak"
                          },
                          {
                            "text": "     [ _CityObject ]",
                            "type": "text"
                          }
                        ],
                        "type": "paragraph"
                      }
                    ],
                    "type": "table_cell"
                  },
                  {
                    "attrs": {
                      "background": null,
                      "colspan": null,
                      "colwidth": null,
                      "rowspan": null
                    },
                    "content": [
                      {
                        "attrs": {
                          "resourceID": "urn:metanorma:doc-part:_8048dcce-5698-a3fe-c455-62a9475a7a5a"
                        },
                        "content": [
                          {
                            "text": "core::RelativeToTerrainType [0..1]",
                            "type": "text"
                          }
                        ],
                        "type": "paragraph"
                      }
                    ],
                    "type": "table_cell"
                  },
                  {
                    "attrs": {
                      "background": null,
                      "colspan": null,
                      "colwidth": null,
                      "rowspan": null
                    },
                    "content": [
                      {
                        "attrs": {
                          "resourceID": "urn:metanorma:doc-part:_bbd793a2-9d5a-6485-0842-66df219927ec"
                        },
                        "content": [
                          {
                            "text": "地表面との相対的な位置関係。標準製品仕様書では使用しない。",
                            "type": "text"
                          }
                        ],
                        "type": "paragraph"
                      }
                    ],
                    "type": "table_cell"
                  }
                ],
                "type": "table_row"
              },
              {
                "content": [
                  {
                    "attrs": {
                      "background": null,
                      "colspan": null,
                      "colwidth": null,
                      "rowspan": null
                    },
                    "content": [
                      {
                        "attrs": {
                          "resourceID": "urn:metanorma:doc-part:_19fd157c-aaae-84a1-aea9-e2c2c95cf8b6"
                        },
                        "content": [
                          {
                            "text": "core:relativeToWater",
                            "type": "text"
                          },
                          {
                            "type": "linebreak"
                          },
                          {
                            "text": "     [ _CityObject ]",
                            "type": "text"
                          }
                        ],
                        "type": "paragraph"
                      }
                    ],
                    "type": "table_cell"
                  },
                  {
                    "attrs": {
                      "background": null,
                      "colspan": null,
                      "colwidth": null,
                      "rowspan": null
                    },
                    "content": [
                      {
                        "attrs": {
                          "resourceID": "urn:metanorma:doc-part:_d656a775-9591-653d-8e59-1cac0fe8d51d"
                        },
                        "content": [
                          {
                            "text": "core::RelativeToWaterType [0..1]",
                            "type": "text"
                          }
                        ],
                        "type": "paragraph"
                      }
                    ],
                    "type": "table_cell"
                  },
                  {
                    "attrs": {
                      "background": null,
                      "colspan": null,
                      "colwidth": null,
                      "rowspan": null
                    },
                    "content": [
                      {
                        "attrs": {
                          "resourceID": "urn:metanorma:doc-part:_b06f5de8-a73f-466b-3438-d8ba3d6e21f3"
                        },
                        "content": [
                          {
                            "text": "水面との相対的な位置関係。標準製品仕様書では使用しない。",
                            "type": "text"
                          }
                        ],
                        "type": "paragraph"
                      }
                    ],
                    "type": "table_cell"
                  }
                ],
                "type": "table_row"
              },
              {
                "content": [
                  {
                    "attrs": {
                      "background": null,
                      "colspan": "3",
                      "colwidth": null,
                      "rowspan": null
                    },
                    "content": [
                      {
                        "attrs": {
                          "resourceID": ""
                        },
                        "content": [
                          {
                            "text": "自身に定義された属性",
                            "type": "text"
                          }
                        ],
                        "type": "paragraph"
                      }
                    ],
                    "type": "table_header"
                  }
                ],
                "type": "table_row"
              },
              {
                "content": [
                  {
                    "attrs": {
                      "background": null,
                      "colspan": null,
                      "colwidth": null,
                      "rowspan": null
                    },
                    "content": [
                      {
                        "attrs": {
                          "resourceID": ""
                        },
                        "content": [
                          {
                            "text": "属性名",
                            "type": "text"
                          }
                        ],
                        "type": "paragraph"
                      }
                    ],
                    "type": "table_header"
                  },
                  {
                    "attrs": {
                      "background": null,
                      "colspan": null,
                      "colwidth": null,
                      "rowspan": null
                    },
                    "content": [
                      {
                        "attrs": {
                          "resourceID": ""
                        },
                        "content": [
                          {
                            "text": "属性の型及び多重度",
                            "type": "text"
                          }
                        ],
                        "type": "paragraph"
                      }
                    ],
                    "type": "table_header"
                  },
                  {
                    "attrs": {
                      "background": null,
                      "colspan": null,
                      "colwidth": null,
                      "rowspan": null
                    },
                    "content": [
                      {
                        "attrs": {
                          "resourceID": ""
                        },
                        "content": [
                          {
                            "text": "定義",
                            "type": "text"
                          }
                        ],
                        "type": "paragraph"
                      }
                    ],
                    "type": "table_header"
                  }
                ],
                "type": "table_row"
              },
              {
                "content": [
                  {
                    "attrs": {
                      "background": null,
                      "colspan": null,
                      "colwidth": null,
                      "rowspan": null
                    },
                    "content": [
                      {
                        "attrs": {
                          "resourceID": "urn:metanorma:doc-part:_0aac7d6d-971e-1707-084c-655bd90d88ab"
                        },
                        "content": [
                          {
                            "text": "dem:lod",
                            "type": "text"
                          },
                          {
                            "type": "linebreak"
                          },
                          {
                            "text": "     [ ReliefFeature ]",
                            "type": "text"
                          }
                        ],
                        "type": "paragraph"
                      }
                    ],
                    "type": "table_cell"
                  },
                  {
                    "attrs": {
                      "background": null,
                      "colspan": null,
                      "colwidth": null,
                      "rowspan": null
                    },
                    "content": [
                      {
                        "attrs": {
                          "resourceID": "urn:metanorma:doc-part:_3c64f6c2-d511-968f-7431-5a07e69f8e4a"
                        },
                        "content": [
                          {
                            "text": "core::integerBetween0and4 [1..1]",
                            "type": "text"
                          }
                        ],
                        "type": "paragraph"
                      }
                    ],
                    "type": "table_cell"
                  },
                  {
                    "attrs": {
                      "background": null,
                      "colspan": null,
                      "colwidth": null,
                      "rowspan": null
                    },
                    "content": [
                      {
                        "attrs": {
                          "resourceID": "urn:metanorma:doc-part:_c5856a2a-9c30-004a-ec5f-c0990d0dd5ec"
                        },
                        "content": [
                          {
                            "text": "この地形に適用されるLOD0～3までの半角数字のいずれかとする。LOD1の場合は1となる。",
                            "type": "text"
                          },
                          {
                            "type": "linebreak"
                          },
                          {
                            "text": " dem:ReliefFeatureがもつdem:TINRelief、dem:MassPointRelief又はdem:BreaklineReliefのlodと一致させる。",
                            "type": "text"
                          }
                        ],
                        "type": "paragraph"
                      }
                    ],
                    "type": "table_cell"
                  }
                ],
                "type": "table_row"
              },
              {
                "content": [
                  {
                    "attrs": {
                      "background": null,
                      "colspan": "3",
                      "colwidth": null,
                      "rowspan": null
                    },
                    "content": [
                      {
                        "attrs": {
                          "resourceID": ""
                        },
                        "content": [
                          {
                            "text": "継承する関連役割",
                            "type": "text"
                          }
                        ],
                        "type": "paragraph"
                      }
                    ],
                    "type": "table_header"
                  }
                ],
                "type": "table_row"
              },
              {
                "content": [
                  {
                    "attrs": {
                      "background": null,
                      "colspan": null,
                      "colwidth": null,
                      "rowspan": null
                    },
                    "content": [
                      {
                        "attrs": {
                          "resourceID": ""
                        },
                        "content": [
                          {
                            "text": "関連役割名",
                            "type": "text"
                          }
                        ],
                        "type": "paragraph"
                      }
                    ],
                    "type": "table_header"
                  },
                  {
                    "attrs": {
                      "background": null,
                      "colspan": null,
                      "colwidth": null,
                      "rowspan": null
                    },
                    "content": [
                      {
                        "attrs": {
                          "resourceID": ""
                        },
                        "content": [
                          {
                            "text": "関連役割の型及び多重度",
                            "type": "text"
                          }
                        ],
                        "type": "paragraph"
                      }
                    ],
                    "type": "table_header"
                  },
                  {
                    "attrs": {
                      "background": null,
                      "colspan": null,
                      "colwidth": null,
                      "rowspan": null
                    },
                    "content": [
                      {
                        "attrs": {
                          "resourceID": ""
                        },
                        "content": [
                          {
                            "text": "定義",
                            "type": "text"
                          }
                        ],
                        "type": "paragraph"
                      }
                    ],
                    "type": "table_header"
                  }
                ],
                "type": "table_row"
              },
              {
                "content": [
                  {
                    "attrs": {
                      "background": null,
                      "colspan": null,
                      "colwidth": null,
                      "rowspan": null
                    },
                    "content": [
                      {
                        "attrs": {
                          "resourceID": "urn:metanorma:doc-part:_c17776ab-e6b1-d621-fb99-3c221c1a7164"
                        },
                        "content": [
                          {
                            "text": "core:externalReference",
                            "type": "text"
                          },
                          {
                            "type": "linebreak"
                          },
                          {
                            "text": "             [ _CityObject ]",
                            "type": "text"
                          }
                        ],
                        "type": "paragraph"
                      }
                    ],
                    "type": "table_cell"
                  },
                  {
                    "attrs": {
                      "background": null,
                      "colspan": null,
                      "colwidth": null,
                      "rowspan": null
                    },
                    "content": [
                      {
                        "attrs": {
                          "resourceID": "urn:metanorma:doc-part:_b5e764a2-496c-d7cd-edb2-e1bdee65de90"
                        },
                        "content": [
                          {
                            "text": "core:ExternalReference [0..*]",
                            "type": "text"
                          }
                        ],
                        "type": "paragraph"
                      }
                    ],
                    "type": "table_cell"
                  },
                  {
                    "attrs": {
                      "background": null,
                      "colspan": null,
                      "colwidth": null,
                      "rowspan": null
                    },
                    "content": [
                      {
                        "attrs": {
                          "resourceID": "urn:metanorma:doc-part:_0c43a765-440f-6054-07fd-195cd87734c8"
                        },
                        "content": [
                          {
                            "text": "外部への参照。標準製品仕様書では使用しない。",
                            "type": "text"
                          }
                        ],
                        "type": "paragraph"
                      }
                    ],
                    "type": "table_cell"
                  }
                ],
                "type": "table_row"
              },
              {
                "content": [
                  {
                    "attrs": {
                      "background": null,
                      "colspan": null,
                      "colwidth": null,
                      "rowspan": null
                    },
                    "content": [
                      {
                        "attrs": {
                          "resourceID": "urn:metanorma:doc-part:_4b1822d7-995c-3207-5801-58b582c0ee1b"
                        },
                        "content": [
                          {
                            "text": "gen:dateAttribute",
                            "type": "text"
                          },
                          {
                            "type": "linebreak"
                          },
                          {
                            "text": "             [ _CityObject ]",
                            "type": "text"
                          }
                        ],
                        "type": "paragraph"
                      }
                    ],
                    "type": "table_cell"
                  },
                  {
                    "attrs": {
                      "background": null,
                      "colspan": null,
                      "colwidth": null,
                      "rowspan": null
                    },
                    "content": [
                      {
                        "attrs": {
                          "resourceID": "urn:metanorma:doc-part:_65e077a5-01d8-9f42-3498-a26d34fb8d6a"
                        },
                        "content": [
                          {
                            "text": "gen:dateAttribute [0..*]",
                            "type": "text"
                          }
                        ],
                        "type": "paragraph"
                      }
                    ],
                    "type": "table_cell"
                  },
                  {
                    "attrs": {
                      "background": null,
                      "colspan": null,
                      "colwidth": null,
                      "rowspan": null
                    },
                    "content": [
                      {
                        "attrs": {
                          "resourceID": "urn:metanorma:doc-part:_cbeffdb5-be68-6c11-849c-1ad481695e2c"
                        },
                        "content": [
                          {
                            "text": "日付型属性。属性を追加したい場合に使用する。",
                            "type": "text"
                          }
                        ],
                        "type": "paragraph"
                      }
                    ],
                    "type": "table_cell"
                  }
                ],
                "type": "table_row"
              },
              {
                "content": [
                  {
                    "attrs": {
                      "background": null,
                      "colspan": null,
                      "colwidth": null,
                      "rowspan": null
                    },
                    "content": [
                      {
                        "attrs": {
                          "resourceID": "urn:metanorma:doc-part:_3fbe623c-b237-c57f-581f-fa061ea74ad3"
                        },
                        "content": [
                          {
                            "text": "gen:doubleAttribute",
                            "type": "text"
                          },
                          {
                            "type": "linebreak"
                          },
                          {
                            "text": "             [ _CityObject ]",
                            "type": "text"
                          }
                        ],
                        "type": "paragraph"
                      }
                    ],
                    "type": "table_cell"
                  },
                  {
                    "attrs": {
                      "background": null,
                      "colspan": null,
                      "colwidth": null,
                      "rowspan": null
                    },
                    "content": [
                      {
                        "attrs": {
                          "resourceID": "urn:metanorma:doc-part:_764bda04-a4bc-80e6-cfd5-53ab5165f872"
                        },
                        "content": [
                          {
                            "text": "gen:doubleAttribute [0..*]",
                            "type": "text"
                          }
                        ],
                        "type": "paragraph"
                      }
                    ],
                    "type": "table_cell"
                  },
                  {
                    "attrs": {
                      "background": null,
                      "colspan": null,
                      "colwidth": null,
                      "rowspan": null
                    },
                    "content": [
                      {
                        "attrs": {
                          "resourceID": "urn:metanorma:doc-part:_1a2513e0-1b1f-b7c2-4072-5a536f20290d"
                        },
                        "content": [
                          {
                            "text": "実数型属性。属性を追加したい場合に使用する。",
                            "type": "text"
                          }
                        ],
                        "type": "paragraph"
                      }
                    ],
                    "type": "table_cell"
                  }
                ],
                "type": "table_row"
              },
              {
                "content": [
                  {
                    "attrs": {
                      "background": null,
                      "colspan": null,
                      "colwidth": null,
                      "rowspan": null
                    },
                    "content": [
                      {
                        "attrs": {
                          "resourceID": "urn:metanorma:doc-part:_0c66d9cc-1a80-6ab7-2fb8-74b1cf70a391"
                        },
                        "content": [
                          {
                            "text": "gen:genericAttributeSet",
                            "type": "text"
                          },
                          {
                            "type": "linebreak"
                          },
                          {
                            "text": "             [ _CityObject ]",
                            "type": "text"
                          }
                        ],
                        "type": "paragraph"
                      }
                    ],
                    "type": "table_cell"
                  },
                  {
                    "attrs": {
                      "background": null,
                      "colspan": null,
                      "colwidth": null,
                      "rowspan": null
                    },
                    "content": [
                      {
                        "attrs": {
                          "resourceID": "urn:metanorma:doc-part:_2166e779-4205-3f5f-a3c2-7e662d9c9469"
                        },
                        "content": [
                          {
                            "text": "gen:genericAttributeSet [0..*]",
                            "type": "text"
                          }
                        ],
                        "type": "paragraph"
                      }
                    ],
                    "type": "table_cell"
                  },
                  {
                    "attrs": {
                      "background": null,
                      "colspan": null,
                      "colwidth": null,
                      "rowspan": null
                    },
                    "content": [
                      {
                        "attrs": {
                          "resourceID": "urn:metanorma:doc-part:_88998121-1595-3a20-a2fe-f39da4bdec5f"
                        },
                        "content": [
                          {
                            "text": "汎用属性のセット。属性を追加したい場合に使用する。",
                            "type": "text"
                          }
                        ],
                        "type": "paragraph"
                      }
                    ],
                    "type": "table_cell"
                  }
                ],
                "type": "table_row"
              },
              {
                "content": [
                  {
                    "attrs": {
                      "background": null,
                      "colspan": null,
                      "colwidth": null,
                      "rowspan": null
                    },
                    "content": [
                      {
                        "attrs": {
                          "resourceID": "urn:metanorma:doc-part:_11c49575-a8c9-f6e3-ae02-384e02d9ae26"
                        },
                        "content": [
                          {
                            "text": "gen:intAttribute",
                            "type": "text"
                          },
                          {
                            "type": "linebreak"
                          },
                          {
                            "text": "             [ _CityObject ]",
                            "type": "text"
                          }
                        ],
                        "type": "paragraph"
                      }
                    ],
                    "type": "table_cell"
                  },
                  {
                    "attrs": {
                      "background": null,
                      "colspan": null,
                      "colwidth": null,
                      "rowspan": null
                    },
                    "content": [
                      {
                        "attrs": {
                          "resourceID": "urn:metanorma:doc-part:_0f550280-1fbf-809c-4153-67d5e5bdd49e"
                        },
                        "content": [
                          {
                            "text": "gen:intAttribute [0..*]",
                            "type": "text"
                          }
                        ],
                        "type": "paragraph"
                      }
                    ],
                    "type": "table_cell"
                  },
                  {
                    "attrs": {
                      "background": null,
                      "colspan": null,
                      "colwidth": null,
                      "rowspan": null
                    },
                    "content": [
                      {
                        "attrs": {
                          "resourceID": "urn:metanorma:doc-part:_20f82d6e-24be-ef2f-c6ae-4505c6b86c08"
                        },
                        "content": [
                          {
                            "text": "整数型属性。属性を追加したい場合に使用する。",
                            "type": "text"
                          }
                        ],
                        "type": "paragraph"
                      }
                    ],
                    "type": "table_cell"
                  }
                ],
                "type": "table_row"
              },
              {
                "content": [
                  {
                    "attrs": {
                      "background": null,
                      "colspan": null,
                      "colwidth": null,
                      "rowspan": null
                    },
                    "content": [
                      {
                        "attrs": {
                          "resourceID": "urn:metanorma:doc-part:_82ce2c55-2673-5fb5-84c0-c3e01dc5b12c"
                        },
                        "content": [
                          {
                            "text": "gen:measureAttribute",
                            "type": "text"
                          },
                          {
                            "type": "linebreak"
                          },
                          {
                            "text": "             [ _CityObject ]",
                            "type": "text"
                          }
                        ],
                        "type": "paragraph"
                      }
                    ],
                    "type": "table_cell"
                  },
                  {
                    "attrs": {
                      "background": null,
                      "colspan": null,
                      "colwidth": null,
                      "rowspan": null
                    },
                    "content": [
                      {
                        "attrs": {
                          "resourceID": "urn:metanorma:doc-part:_6fa755e9-feff-b44f-3439-538ea84f974c"
                        },
                        "content": [
                          {
                            "text": "gen:measureAttribute [0..*]",
                            "type": "text"
                          }
                        ],
                        "type": "paragraph"
                      }
                    ],
                    "type": "table_cell"
                  },
                  {
                    "attrs": {
                      "background": null,
                      "colspan": null,
                      "colwidth": null,
                      "rowspan": null
                    },
                    "content": [
                      {
                        "attrs": {
                          "resourceID": "urn:metanorma:doc-part:_68f4e2a0-51e6-1c1a-f061-4eff9169475d"
                        },
                        "content": [
                          {
                            "text": "単位付き数値型属性。属性を追加したい場合に使用する。",
                            "type": "text"
                          }
                        ],
                        "type": "paragraph"
                      }
                    ],
                    "type": "table_cell"
                  }
                ],
                "type": "table_row"
              },
              {
                "content": [
                  {
                    "attrs": {
                      "background": null,
                      "colspan": null,
                      "colwidth": null,
                      "rowspan": null
                    },
                    "content": [
                      {
                        "attrs": {
                          "resourceID": "urn:metanorma:doc-part:_3c97b9cc-6e21-9d2f-6d1b-7a5ec88f165e"
                        },
                        "content": [
                          {
                            "text": "gen:stringAttribute",
                            "type": "text"
                          },
                          {
                            "type": "linebreak"
                          },
                          {
                            "text": "             [ _CityObject ]",
                            "type": "text"
                          }
                        ],
                        "type": "paragraph"
                      }
                    ],
                    "type": "table_cell"
                  },
                  {
                    "attrs": {
                      "background": null,
                      "colspan": null,
                      "colwidth": null,
                      "rowspan": null
                    },
                    "content": [
                      {
                        "attrs": {
                          "resourceID": "urn:metanorma:doc-part:_ca7edb75-411e-7ed8-6591-c873ee967640"
                        },
                        "content": [
                          {
                            "text": "gen:stringAttribute [0..*]",
                            "type": "text"
                          }
                        ],
                        "type": "paragraph"
                      }
                    ],
                    "type": "table_cell"
                  },
                  {
                    "attrs": {
                      "background": null,
                      "colspan": null,
                      "colwidth": null,
                      "rowspan": null
                    },
                    "content": [
                      {
                        "attrs": {
                          "resourceID": "urn:metanorma:doc-part:_ac169e86-f422-1af3-4de0-8b4be3ff06e2"
                        },
                        "content": [
                          {
                            "text": "文字列型属性。属性を追加したい場合に使用する。",
                            "type": "text"
                          }
                        ],
                        "type": "paragraph"
                      }
                    ],
                    "type": "table_cell"
                  }
                ],
                "type": "table_row"
              },
              {
                "content": [
                  {
                    "attrs": {
                      "background": null,
                      "colspan": null,
                      "colwidth": null,
                      "rowspan": null
                    },
                    "content": [
                      {
                        "attrs": {
                          "resourceID": "urn:metanorma:doc-part:_407641d7-57bb-8ddf-4380-343c5c1723f3"
                        },
                        "content": [
                          {
                            "text": "gen:uriAttribute",
                            "type": "text"
                          },
                          {
                            "type": "linebreak"
                          },
                          {
                            "text": "             [ _CityObject ]",
                            "type": "text"
                          }
                        ],
                        "type": "paragraph"
                      }
                    ],
                    "type": "table_cell"
                  },
                  {
                    "attrs": {
                      "background": null,
                      "colspan": null,
                      "colwidth": null,
                      "rowspan": null
                    },
                    "content": [
                      {
                        "attrs": {
                          "resourceID": "urn:metanorma:doc-part:_9f3964b5-0e33-f40c-c2ce-89334695f46f"
                        },
                        "content": [
                          {
                            "text": "gen:uriAttribute [0..*]",
                            "type": "text"
                          }
                        ],
                        "type": "paragraph"
                      }
                    ],
                    "type": "table_cell"
                  },
                  {
                    "attrs": {
                      "background": null,
                      "colspan": null,
                      "colwidth": null,
                      "rowspan": null
                    },
                    "content": [
                      {
                        "attrs": {
                          "resourceID": "urn:metanorma:doc-part:_dcbf7f6d-61bb-7850-fa6f-d6302de2a581"
                        },
                        "content": [
                          {
                            "text": "URI型属性。属性を追加したい場合に使用する。",
                            "type": "text"
                          }
                        ],
                        "type": "paragraph"
                      }
                    ],
                    "type": "table_cell"
                  }
                ],
                "type": "table_row"
              },
              {
                "content": [
                  {
                    "attrs": {
                      "background": null,
                      "colspan": null,
                      "colwidth": null,
                      "rowspan": null
                    },
                    "content": [
                      {
                        "attrs": {
                          "resourceID": "urn:metanorma:doc-part:_16a5644b-37f2-9927-9a12-d5dae9177880"
                        },
                        "content": [
                          {
                            "text": "uro:pointCloud",
                            "type": "text"
                          },
                          {
                            "type": "linebreak"
                          },
                          {
                            "text": "             [ _CityObject ]",
                            "type": "text"
                          }
                        ],
                        "type": "paragraph"
                      }
                    ],
                    "type": "table_cell"
                  },
                  {
                    "attrs": {
                      "background": null,
                      "colspan": null,
                      "colwidth": null,
                      "rowspan": null
                    },
                    "content": [
                      {
                        "attrs": {
                          "resourceID": "urn:metanorma:doc-part:_241f9ef6-65a8-d99d-b322-901fb53c36ff"
                        },
                        "content": [
                          {
                            "text": "uro:AbstractPointCloud [0..1]",
                            "type": "text"
                          }
                        ],
                        "type": "paragraph"
                      }
                    ],
                    "type": "table_cell"
                  },
                  {
                    "attrs": {
                      "background": null,
                      "colspan": null,
                      "colwidth": null,
                      "rowspan": null
                    },
                    "content": [
                      {
                        "attrs": {
                          "resourceID": "urn:metanorma:doc-part:_fbf4abcf-ec41-ca26-f950-a17a3524c9c9"
                        },
                        "content": [
                          {
                            "text": "ポイントクラウドへの参照。",
                            "type": "text"
                          }
                        ],
                        "type": "paragraph"
                      }
                    ],
                    "type": "table_cell"
                  }
                ],
                "type": "table_row"
              },
              {
                "content": [
                  {
                    "attrs": {
                      "background": null,
                      "colspan": "3",
                      "colwidth": null,
                      "rowspan": null
                    },
                    "content": [
                      {
                        "attrs": {
                          "resourceID": ""
                        },
                        "content": [
                          {
                            "text": "自身に定義された関連役割",
                            "type": "text"
                          }
                        ],
                        "type": "paragraph"
                      }
                    ],
                    "type": "table_header"
                  }
                ],
                "type": "table_row"
              },
              {
                "content": [
                  {
                    "attrs": {
                      "background": null,
                      "colspan": null,
                      "colwidth": null,
                      "rowspan": null
                    },
                    "content": [
                      {
                        "attrs": {
                          "resourceID": ""
                        },
                        "content": [
                          {
                            "text": "関連役割名",
                            "type": "text"
                          }
                        ],
                        "type": "paragraph"
                      }
                    ],
                    "type": "table_header"
                  },
                  {
                    "attrs": {
                      "background": null,
                      "colspan": null,
                      "colwidth": null,
                      "rowspan": null
                    },
                    "content": [
                      {
                        "attrs": {
                          "resourceID": ""
                        },
                        "content": [
                          {
                            "text": "関連役割の型及び多重度",
                            "type": "text"
                          }
                        ],
                        "type": "paragraph"
                      }
                    ],
                    "type": "table_header"
                  },
                  {
                    "attrs": {
                      "background": null,
                      "colspan": null,
                      "colwidth": null,
                      "rowspan": null
                    },
                    "content": [
                      {
                        "attrs": {
                          "resourceID": ""
                        },
                        "content": [
                          {
                            "text": "定義",
                            "type": "text"
                          }
                        ],
                        "type": "paragraph"
                      }
                    ],
                    "type": "table_header"
                  }
                ],
                "type": "table_row"
              },
              {
                "content": [
                  {
                    "attrs": {
                      "background": null,
                      "colspan": null,
                      "colwidth": null,
                      "rowspan": null
                    },
                    "content": [
                      {
                        "attrs": {
                          "resourceID": "urn:metanorma:doc-part:_ec93ec78-0312-6f54-3bb3-5d2885c7e779"
                        },
                        "content": [
                          {
                            "text": "dem:reliefComponent",
                            "type": "text"
                          },
                          {
                            "type": "linebreak"
                          },
                          {
                            "text": "             [ ReliefFeature ]",
                            "type": "text"
                          }
                        ],
                        "type": "paragraph"
                      }
                    ],
                    "type": "table_cell"
                  },
                  {
                    "attrs": {
                      "background": null,
                      "colspan": null,
                      "colwidth": null,
                      "rowspan": null
                    },
                    "content": [
                      {
                        "attrs": {
                          "resourceID": "urn:metanorma:doc-part:_8d01d563-4414-0751-af52-86acf783feab"
                        },
                        "content": [
                          {
                            "text": "dem:_ReliefComponent [1..*]",
                            "type": "text"
                          }
                        ],
                        "type": "paragraph"
                      }
                    ],
                    "type": "table_cell"
                  },
                  {
                    "attrs": {
                      "background": null,
                      "colspan": null,
                      "colwidth": null,
                      "rowspan": null
                    },
                    "content": [
                      {
                        "attrs": {
                          "resourceID": "urn:metanorma:doc-part:_4df34f19-10f0-463a-6675-763ad7d67d5e"
                        },
                        "content": [
                          {
                            "text": "同じ基準地域メッシュ（第3次地域区画）に限り、dem:TINRelief又はdem:MassPointReliefのいずれか1つを複数もつことができる。",
                            "type": "text"
                          }
                        ],
                        "type": "paragraph"
                      }
                    ],
                    "type": "table_cell"
                  }
                ],
                "type": "table_row"
              },
              {
                "content": [
                  {
                    "attrs": {
                      "background": null,
                      "colspan": null,
                      "colwidth": null,
                      "rowspan": null
                    },
                    "content": [
                      {
                        "attrs": {
                          "resourceID": "urn:metanorma:doc-part:_f8bbe168-efec-8822-4432-023d8666385b"
                        },
                        "content": [
                          {
                            "text": "uro:demDataQualityAttribute",
                            "type": "text"
                          },
                          {
                            "type": "linebreak"
                          },
                          {
                            "text": "             [ ReliefFeature ]",
                            "type": "text"
                          }
                        ],
                        "type": "paragraph"
                      }
                    ],
                    "type": "table_cell"
                  },
                  {
                    "attrs": {
                      "background": null,
                      "colspan": null,
                      "colwidth": null,
                      "rowspan": null
                    },
                    "content": [
                      {
                        "attrs": {
                          "resourceID": "urn:metanorma:doc-part:_234de1fe-d5e9-5da0-5d5e-5454985ebede"
                        },
                        "content": [
                          {
                            "text": "uro:DataQualityAttribute [1..1]",
                            "type": "text"
                          }
                        ],
                        "type": "paragraph"
                      }
                    ],
                    "type": "table_cell"
                  },
                  {
                    "attrs": {
                      "background": null,
                      "colspan": null,
                      "colwidth": null,
                      "rowspan": null
                    },
                    "content": [
                      {
                        "attrs": {
                          "resourceID": "urn:metanorma:doc-part:_6090d531-fe08-7119-c88d-bae1cb2e0d9b"
                        },
                        "content": [
                          {
                            "text": "作成されたデータの品質に関する情報。必須とする。",
                            "type": "text"
                          }
                        ],
                        "type": "paragraph"
                      }
                    ],
                    "type": "table_cell"
                  }
                ],
                "type": "table_row"
              },
              {
                "content": [
                  {
                    "attrs": {
                      "background": null,
                      "colspan": null,
                      "colwidth": null,
                      "rowspan": null
                    },
                    "content": [
                      {
                        "attrs": {
                          "resourceID": "urn:metanorma:doc-part:_a83e931f-7369-a70c-b8a9-8b5b871d52f6"
                        },
                        "content": [
                          {
                            "text": "uro:demKeyValuePairAttribute",
                            "type": "text"
                          },
                          {
                            "type": "linebreak"
                          },
                          {
                            "text": "             [ ReliefFeature ]",
                            "type": "text"
                          }
                        ],
                        "type": "paragraph"
                      }
                    ],
                    "type": "table_cell"
                  },
                  {
                    "attrs": {
                      "background": null,
                      "colspan": null,
                      "colwidth": null,
                      "rowspan": null
                    },
                    "content": [
                      {
                        "attrs": {
                          "resourceID": "urn:metanorma:doc-part:_fbbd92b5-b209-f7f7-88bb-d7c52cd41049"
                        },
                        "content": [
                          {
                            "text": "uro:KeyValuePairAttribute [0..*]",
                            "type": "text"
                          }
                        ],
                        "type": "paragraph"
                      }
                    ],
                    "type": "table_cell"
                  },
                  {
                    "attrs": {
                      "background": null,
                      "colspan": null,
                      "colwidth": null,
                      "rowspan": null
                    },
                    "content": [
                      {
                        "attrs": {
                          "resourceID": "urn:metanorma:doc-part:_c46c8a87-6029-bfb3-30bd-758141c819e5"
                        },
                        "content": [
                          {
                            "text": "コード属性を拡張するための仕組み。コ－ド値以外の属性を拡張する場合は、gen:_GenericAttributeの下位型を使用する。",
                            "type": "text"
                          }
                        ],
                        "type": "paragraph"
                      }
                    ],
                    "type": "table_cell"
                  }
                ],
                "type": "table_row"
              }
            ],
            "type": "table"
          }
        ],
        "type": "tableFigure"
      }
    }
  ]
}
