{
  "title": "4.18.4.1.5  PublicSurveyDataQualityAttribute_geometrySrcDesc.xml",
  "path": "/plateaudocument/toc4/toc4_18/toc4_18_04/toc4_18_04_01/_publicsurveydataqualityattribute_geometrysrcdesc_xml_11",
  "content": [
    {
      "type": "title",
      "content": {
        "content": [
          {
            "text": "4.18.4.1.5\tPublicSurveyDataQualityAttribute_geometrySrcDesc.xml",
            "type": "text"
          }
        ],
        "type": "title"
      }
    },
    {
      "type": "tableFigure",
      "content": {
        "attrs": {
          "resourceID": "urn:metanorma:doc-part:_acf2bb6d-a078-253e-c7d2-2a3b53174762"
        },
        "content": [
          {
            "content": [
              {
                "content": [
                  {
                    "text": "表",
                    "type": "text"
                  }
                ],
                "type": "span"
              },
              {
                "text": "4-787",
                "type": "text"
              }
            ],
            "type": "figCaption"
          },
          {
            "attrs": {
              "colWidths": [
                "12%",
                "88%"
              ]
            },
            "content": [
              {
                "content": [
                  {
                    "attrs": {
                      "background": null,
                      "colspan": null,
                      "colwidth": null,
                      "rowspan": null
                    },
                    "content": [
                      {
                        "attrs": {
                          "resourceID": ""
                        },
                        "content": [
                          {
                            "text": "ファイル名",
                            "type": "text"
                          }
                        ],
                        "type": "paragraph"
                      }
                    ],
                    "type": "table_header"
                  },
                  {
                    "attrs": {
                      "background": null,
                      "colspan": null,
                      "colwidth": null,
                      "rowspan": null
                    },
                    "content": [
                      {
                        "attrs": {
                          "resourceID": ""
                        },
                        "content": [
                          {
                            "text": "PublicSurveyDataQualityAttribute_geometrySrcDesc.xml",
                            "type": "text"
                          }
                        ],
                        "type": "paragraph"
                      }
                    ],
                    "type": "table_header"
                  }
                ],
                "type": "table_row"
              },
              {
                "content": [
                  {
                    "attrs": {
                      "background": null,
                      "colspan": null,
                      "colwidth": null,
                      "rowspan": null
                    },
                    "content": [
                      {
                        "attrs": {
                          "resourceID": ""
                        },
                        "content": [
                          {
                            "text": "ファイルURL",
                            "type": "text"
                          }
                        ],
                        "type": "paragraph"
                      }
                    ],
                    "type": "table_header"
                  },
                  {
                    "attrs": {
                      "background": null,
                      "colspan": null,
                      "colwidth": null,
                      "rowspan": null
                    },
                    "content": [
                      {
                        "attrs": {
                          "resourceID": "urn:metanorma:doc-part:_34cfb294-4c4c-958d-e31c-8ceedbeb8095"
                        },
                        "content": [
                          {
                            "attrs": {
                              "href": "https://www.geospatial.jp/iur/codelists/3.2/PublicSurveyDataQualityAttribute_geometrySrcDesc.xml"
                            },
                            "type": "external_link"
                          }
                        ],
                        "type": "paragraph"
                      }
                    ],
                    "type": "table_cell"
                  }
                ],
                "type": "table_row"
              },
              {
                "content": [
                  {
                    "attrs": {
                      "background": null,
                      "colspan": null,
                      "colwidth": null,
                      "rowspan": null
                    },
                    "content": [
                      {
                        "attrs": {
                          "resourceID": ""
                        },
                        "content": [
                          {
                            "text": "コード",
                            "type": "text"
                          }
                        ],
                        "type": "paragraph"
                      }
                    ],
                    "type": "table_header"
                  },
                  {
                    "attrs": {
                      "background": null,
                      "colspan": null,
                      "colwidth": null,
                      "rowspan": null
                    },
                    "content": [
                      {
                        "attrs": {
                          "resourceID": ""
                        },
                        "content": [
                          {
                            "text": "説明",
                            "type": "text"
                          }
                        ],
                        "type": "paragraph"
                      }
                    ],
                    "type": "table_header"
                  }
                ],
                "type": "table_row"
              },
              {
                "content": [
                  {
                    "attrs": {
                      "background": null,
                      "colspan": null,
                      "colwidth": null,
                      "rowspan": null
                    },
                    "content": [
                      {
                        "attrs": {
                          "resourceID": "urn:metanorma:doc-part:_c330bbf3-a180-1874-b6b1-4313cf568b54"
                        },
                        "content": [
                          {
                            "text": "001",
                            "type": "text"
                          }
                        ],
                        "type": "paragraph"
                      }
                    ],
                    "type": "table_cell"
                  },
                  {
                    "attrs": {
                      "background": null,
                      "colspan": null,
                      "colwidth": null,
                      "rowspan": null
                    },
                    "content": [
                      {
                        "attrs": {
                          "resourceID": "urn:metanorma:doc-part:_040b9773-7479-8313-7b8e-b90948b55818"
                        },
                        "content": [
                          {
                            "text": "現地測量の測量成果",
                            "type": "text"
                          }
                        ],
                        "type": "paragraph"
                      }
                    ],
                    "type": "table_cell"
                  }
                ],
                "type": "table_row"
              },
              {
                "content": [
                  {
                    "attrs": {
                      "background": null,
                      "colspan": null,
                      "colwidth": null,
                      "rowspan": null
                    },
                    "content": [
                      {
                        "attrs": {
                          "resourceID": "urn:metanorma:doc-part:_6a7be4c2-8f80-0bb0-83b1-d4d8942cd6b6"
                        },
                        "content": [
                          {
                            "text": "002",
                            "type": "text"
                          }
                        ],
                        "type": "paragraph"
                      }
                    ],
                    "type": "table_cell"
                  },
                  {
                    "attrs": {
                      "background": null,
                      "colspan": null,
                      "colwidth": null,
                      "rowspan": null
                    },
                    "content": [
                      {
                        "attrs": {
                          "resourceID": "urn:metanorma:doc-part:_be91752e-1f2e-51cb-947e-fce2c010f66c"
                        },
                        "content": [
                          {
                            "text": "UAV写真測量の測量成果",
                            "type": "text"
                          }
                        ],
                        "type": "paragraph"
                      }
                    ],
                    "type": "table_cell"
                  }
                ],
                "type": "table_row"
              },
              {
                "content": [
                  {
                    "attrs": {
                      "background": null,
                      "colspan": null,
                      "colwidth": null,
                      "rowspan": null
                    },
                    "content": [
                      {
                        "attrs": {
                          "resourceID": "urn:metanorma:doc-part:_571023a2-8170-4d5e-9ade-c03a11111b9d"
                        },
                        "content": [
                          {
                            "text": "003",
                            "type": "text"
                          }
                        ],
                        "type": "paragraph"
                      }
                    ],
                    "type": "table_cell"
                  },
                  {
                    "attrs": {
                      "background": null,
                      "colspan": null,
                      "colwidth": null,
                      "rowspan": null
                    },
                    "content": [
                      {
                        "attrs": {
                          "resourceID": "urn:metanorma:doc-part:_1c20d8f7-f18a-da8f-8519-173abf2039e8"
                        },
                        "content": [
                          {
                            "text": "空中写真測量の測量成果",
                            "type": "text"
                          }
                        ],
                        "type": "paragraph"
                      }
                    ],
                    "type": "table_cell"
                  }
                ],
                "type": "table_row"
              },
              {
                "content": [
                  {
                    "attrs": {
                      "background": null,
                      "colspan": null,
                      "colwidth": null,
                      "rowspan": null
                    },
                    "content": [
                      {
                        "attrs": {
                          "resourceID": "urn:metanorma:doc-part:_c679c2ef-28df-9f79-3ba4-5d7a0e361867"
                        },
                        "content": [
                          {
                            "text": "004",
                            "type": "text"
                          }
                        ],
                        "type": "paragraph"
                      }
                    ],
                    "type": "table_cell"
                  },
                  {
                    "attrs": {
                      "background": null,
                      "colspan": null,
                      "colwidth": null,
                      "rowspan": null
                    },
                    "content": [
                      {
                        "attrs": {
                          "resourceID": "urn:metanorma:doc-part:_c093010f-6c6b-1441-9cb0-0cc4d822d7ec"
                        },
                        "content": [
                          {
                            "text": "既成図数値化の測量成果",
                            "type": "text"
                          }
                        ],
                        "type": "paragraph"
                      }
                    ],
                    "type": "table_cell"
                  }
                ],
                "type": "table_row"
              },
              {
                "content": [
                  {
                    "attrs": {
                      "background": null,
                      "colspan": null,
                      "colwidth": null,
                      "rowspan": null
                    },
                    "content": [
                      {
                        "attrs": {
                          "resourceID": "urn:metanorma:doc-part:_d7c52dd4-1b0f-5748-a5c5-4d430fdbf645"
                        },
                        "content": [
                          {
                            "text": "005",
                            "type": "text"
                          }
                        ],
                        "type": "paragraph"
                      }
                    ],
                    "type": "table_cell"
                  },
                  {
                    "attrs": {
                      "background": null,
                      "colspan": null,
                      "colwidth": null,
                      "rowspan": null
                    },
                    "content": [
                      {
                        "attrs": {
                          "resourceID": "urn:metanorma:doc-part:_ad404a96-c871-2703-cbe3-edfa3df3f160"
                        },
                        "content": [
                          {
                            "text": "修正測量の測量成果",
                            "type": "text"
                          }
                        ],
                        "type": "paragraph"
                      }
                    ],
                    "type": "table_cell"
                  }
                ],
                "type": "table_row"
              },
              {
                "content": [
                  {
                    "attrs": {
                      "background": null,
                      "colspan": null,
                      "colwidth": null,
                      "rowspan": null
                    },
                    "content": [
                      {
                        "attrs": {
                          "resourceID": "urn:metanorma:doc-part:_8e9baebc-8e67-5dbc-5d20-f7b4aaa6e0c9"
                        },
                        "content": [
                          {
                            "text": "006",
                            "type": "text"
                          }
                        ],
                        "type": "paragraph"
                      }
                    ],
                    "type": "table_cell"
                  },
                  {
                    "attrs": {
                      "background": null,
                      "colspan": null,
                      "colwidth": null,
                      "rowspan": null
                    },
                    "content": [
                      {
                        "attrs": {
                          "resourceID": "urn:metanorma:doc-part:_2a53d5c9-6592-b646-6fb7-1882313125b9"
                        },
                        "content": [
                          {
                            "text": "写真地図作成の測量成果",
                            "type": "text"
                          }
                        ],
                        "type": "paragraph"
                      }
                    ],
                    "type": "table_cell"
                  }
                ],
                "type": "table_row"
              },
              {
                "content": [
                  {
                    "attrs": {
                      "background": null,
                      "colspan": null,
                      "colwidth": null,
                      "rowspan": null
                    },
                    "content": [
                      {
                        "attrs": {
                          "resourceID": "urn:metanorma:doc-part:_6a733d0b-7174-e80f-2692-40a599549c04"
                        },
                        "content": [
                          {
                            "text": "007",
                            "type": "text"
                          }
                        ],
                        "type": "paragraph"
                      }
                    ],
                    "type": "table_cell"
                  },
                  {
                    "attrs": {
                      "background": null,
                      "colspan": null,
                      "colwidth": null,
                      "rowspan": null
                    },
                    "content": [
                      {
                        "attrs": {
                          "resourceID": "urn:metanorma:doc-part:_b8dc9065-e0b4-df28-5a2e-cbea9db73a06"
                        },
                        "content": [
                          {
                            "text": "地図編集の測量成果",
                            "type": "text"
                          }
                        ],
                        "type": "paragraph"
                      }
                    ],
                    "type": "table_cell"
                  }
                ],
                "type": "table_row"
              },
              {
                "content": [
                  {
                    "attrs": {
                      "background": null,
                      "colspan": null,
                      "colwidth": null,
                      "rowspan": null
                    },
                    "content": [
                      {
                        "attrs": {
                          "resourceID": "urn:metanorma:doc-part:_1950c781-1be0-797b-43ff-e1d501d7ffed"
                        },
                        "content": [
                          {
                            "text": "008",
                            "type": "text"
                          }
                        ],
                        "type": "paragraph"
                      }
                    ],
                    "type": "table_cell"
                  },
                  {
                    "attrs": {
                      "background": null,
                      "colspan": null,
                      "colwidth": null,
                      "rowspan": null
                    },
                    "content": [
                      {
                        "attrs": {
                          "resourceID": "urn:metanorma:doc-part:_91146d49-0f22-82d8-0783-3f82b7d8fd2c"
                        },
                        "content": [
                          {
                            "text": "地上レーザ測量の測量成果",
                            "type": "text"
                          }
                        ],
                        "type": "paragraph"
                      }
                    ],
                    "type": "table_cell"
                  }
                ],
                "type": "table_row"
              },
              {
                "content": [
                  {
                    "attrs": {
                      "background": null,
                      "colspan": null,
                      "colwidth": null,
                      "rowspan": null
                    },
                    "content": [
                      {
                        "attrs": {
                          "resourceID": "urn:metanorma:doc-part:_09f3c589-38ef-6cdd-2fe2-735707e85997"
                        },
                        "content": [
                          {
                            "text": "009",
                            "type": "text"
                          }
                        ],
                        "type": "paragraph"
                      }
                    ],
                    "type": "table_cell"
                  },
                  {
                    "attrs": {
                      "background": null,
                      "colspan": null,
                      "colwidth": null,
                      "rowspan": null
                    },
                    "content": [
                      {
                        "attrs": {
                          "resourceID": "urn:metanorma:doc-part:_c9f97b20-bc6b-ba39-725b-6ebcbdcbb924"
                        },
                        "content": [
                          {
                            "text": "UAV写真点群測量の測量成果",
                            "type": "text"
                          }
                        ],
                        "type": "paragraph"
                      }
                    ],
                    "type": "table_cell"
                  }
                ],
                "type": "table_row"
              },
              {
                "content": [
                  {
                    "attrs": {
                      "background": null,
                      "colspan": null,
                      "colwidth": null,
                      "rowspan": null
                    },
                    "content": [
                      {
                        "attrs": {
                          "resourceID": "urn:metanorma:doc-part:_1ee3a2ac-4707-89e9-843a-579c6b5d1545"
                        },
                        "content": [
                          {
                            "text": "010",
                            "type": "text"
                          }
                        ],
                        "type": "paragraph"
                      }
                    ],
                    "type": "table_cell"
                  },
                  {
                    "attrs": {
                      "background": null,
                      "colspan": null,
                      "colwidth": null,
                      "rowspan": null
                    },
                    "content": [
                      {
                        "attrs": {
                          "resourceID": "urn:metanorma:doc-part:_2e96b9a2-f953-525d-09ac-1a7a5c84a66a"
                        },
                        "content": [
                          {
                            "text": "UAVレーザ測量の測量成果",
                            "type": "text"
                          }
                        ],
                        "type": "paragraph"
                      }
                    ],
                    "type": "table_cell"
                  }
                ],
                "type": "table_row"
              },
              {
                "content": [
                  {
                    "attrs": {
                      "background": null,
                      "colspan": null,
                      "colwidth": null,
                      "rowspan": null
                    },
                    "content": [
                      {
                        "attrs": {
                          "resourceID": "urn:metanorma:doc-part:_a07d4f8d-acf2-142d-cbc1-8f02488d7994"
                        },
                        "content": [
                          {
                            "text": "011",
                            "type": "text"
                          }
                        ],
                        "type": "paragraph"
                      }
                    ],
                    "type": "table_cell"
                  },
                  {
                    "attrs": {
                      "background": null,
                      "colspan": null,
                      "colwidth": null,
                      "rowspan": null
                    },
                    "content": [
                      {
                        "attrs": {
                          "resourceID": "urn:metanorma:doc-part:_21df4955-1e5d-c8e8-54ef-1d6940e8b0b5"
                        },
                        "content": [
                          {
                            "text": "車載写真レーザ測量の測量成果",
                            "type": "text"
                          }
                        ],
                        "type": "paragraph"
                      }
                    ],
                    "type": "table_cell"
                  }
                ],
                "type": "table_row"
              },
              {
                "content": [
                  {
                    "attrs": {
                      "background": null,
                      "colspan": null,
                      "colwidth": null,
                      "rowspan": null
                    },
                    "content": [
                      {
                        "attrs": {
                          "resourceID": "urn:metanorma:doc-part:_21872b02-14c0-8655-c071-493d135d5cde"
                        },
                        "content": [
                          {
                            "text": "012",
                            "type": "text"
                          }
                        ],
                        "type": "paragraph"
                      }
                    ],
                    "type": "table_cell"
                  },
                  {
                    "attrs": {
                      "background": null,
                      "colspan": null,
                      "colwidth": null,
                      "rowspan": null
                    },
                    "content": [
                      {
                        "attrs": {
                          "resourceID": "urn:metanorma:doc-part:_874cbd7e-a5ed-cfc8-80dc-c34e2158f07e"
                        },
                        "content": [
                          {
                            "text": "航空レーザ測量の測量成果",
                            "type": "text"
                          }
                        ],
                        "type": "paragraph"
                      }
                    ],
                    "type": "table_cell"
                  }
                ],
                "type": "table_row"
              },
              {
                "content": [
                  {
                    "attrs": {
                      "background": null,
                      "colspan": null,
                      "colwidth": null,
                      "rowspan": null
                    },
                    "content": [
                      {
                        "attrs": {
                          "resourceID": "urn:metanorma:doc-part:_71a61fa2-bc44-16be-dba5-b9cfb244227e"
                        },
                        "content": [
                          {
                            "text": "013",
                            "type": "text"
                          }
                        ],
                        "type": "paragraph"
                      }
                    ],
                    "type": "table_cell"
                  },
                  {
                    "attrs": {
                      "background": null,
                      "colspan": null,
                      "colwidth": null,
                      "rowspan": null
                    },
                    "content": [
                      {
                        "attrs": {
                          "resourceID": "urn:metanorma:doc-part:_d6c1d43e-369b-f7b1-6ed8-e3b6e84e8c90"
                        },
                        "content": [
                          {
                            "text": "航空レーザ測深測量の測量成果",
                            "type": "text"
                          }
                        ],
                        "type": "paragraph"
                      }
                    ],
                    "type": "table_cell"
                  }
                ],
                "type": "table_row"
              },
              {
                "content": [
                  {
                    "attrs": {
                      "background": null,
                      "colspan": null,
                      "colwidth": null,
                      "rowspan": null
                    },
                    "content": [
                      {
                        "attrs": {
                          "resourceID": "urn:metanorma:doc-part:_7a1beaa5-a298-2b39-70f7-605525bb5188"
                        },
                        "content": [
                          {
                            "text": "014",
                            "type": "text"
                          }
                        ],
                        "type": "paragraph"
                      }
                    ],
                    "type": "table_cell"
                  },
                  {
                    "attrs": {
                      "background": null,
                      "colspan": null,
                      "colwidth": null,
                      "rowspan": null
                    },
                    "content": [
                      {
                        "attrs": {
                          "resourceID": "urn:metanorma:doc-part:_dda0ff2f-c80d-b0e2-6d62-995a9df833f0"
                        },
                        "content": [
                          {
                            "text": "路線測量の測量成果",
                            "type": "text"
                          }
                        ],
                        "type": "paragraph"
                      }
                    ],
                    "type": "table_cell"
                  }
                ],
                "type": "table_row"
              },
              {
                "content": [
                  {
                    "attrs": {
                      "background": null,
                      "colspan": null,
                      "colwidth": null,
                      "rowspan": null
                    },
                    "content": [
                      {
                        "attrs": {
                          "resourceID": "urn:metanorma:doc-part:_05a70c4b-d46c-2061-b929-8cc744fcfe35"
                        },
                        "content": [
                          {
                            "text": "015",
                            "type": "text"
                          }
                        ],
                        "type": "paragraph"
                      }
                    ],
                    "type": "table_cell"
                  },
                  {
                    "attrs": {
                      "background": null,
                      "colspan": null,
                      "colwidth": null,
                      "rowspan": null
                    },
                    "content": [
                      {
                        "attrs": {
                          "resourceID": "urn:metanorma:doc-part:_a5fcd4e2-3b9c-7909-02f8-cd3c53214c93"
                        },
                        "content": [
                          {
                            "text": "河川測量の測量成果",
                            "type": "text"
                          }
                        ],
                        "type": "paragraph"
                      }
                    ],
                    "type": "table_cell"
                  }
                ],
                "type": "table_row"
              },
              {
                "content": [
                  {
                    "attrs": {
                      "background": null,
                      "colspan": null,
                      "colwidth": null,
                      "rowspan": null
                    },
                    "content": [
                      {
                        "attrs": {
                          "resourceID": "urn:metanorma:doc-part:_f8e6b918-18e3-9904-a1fd-d8b8e8fc6883"
                        },
                        "content": [
                          {
                            "text": "016",
                            "type": "text"
                          }
                        ],
                        "type": "paragraph"
                      }
                    ],
                    "type": "table_cell"
                  },
                  {
                    "attrs": {
                      "background": null,
                      "colspan": null,
                      "colwidth": null,
                      "rowspan": null
                    },
                    "content": [
                      {
                        "attrs": {
                          "resourceID": "urn:metanorma:doc-part:_a4de0232-5d44-c9a1-1b9d-26407f677412"
                        },
                        "content": [
                          {
                            "text": "用地測量の測量成果",
                            "type": "text"
                          }
                        ],
                        "type": "paragraph"
                      }
                    ],
                    "type": "table_cell"
                  }
                ],
                "type": "table_row"
              },
              {
                "content": [
                  {
                    "attrs": {
                      "background": null,
                      "colspan": null,
                      "colwidth": null,
                      "rowspan": null
                    },
                    "content": [
                      {
                        "attrs": {
                          "resourceID": "urn:metanorma:doc-part:_7ddcaee9-79c0-7c69-d378-e9e93b314755"
                        },
                        "content": [
                          {
                            "text": "017",
                            "type": "text"
                          }
                        ],
                        "type": "paragraph"
                      }
                    ],
                    "type": "table_cell"
                  },
                  {
                    "attrs": {
                      "background": null,
                      "colspan": null,
                      "colwidth": null,
                      "rowspan": null
                    },
                    "content": [
                      {
                        "attrs": {
                          "resourceID": "urn:metanorma:doc-part:_181d9e1a-4764-67ee-3797-38f7b319c7f3"
                        },
                        "content": [
                          {
                            "text": "その他の応用測量の測量成果",
                            "type": "text"
                          }
                        ],
                        "type": "paragraph"
                      }
                    ],
                    "type": "table_cell"
                  }
                ],
                "type": "table_row"
              },
              {
                "content": [
                  {
                    "attrs": {
                      "background": null,
                      "colspan": null,
                      "colwidth": null,
                      "rowspan": null
                    },
                    "content": [
                      {
                        "attrs": {
                          "resourceID": "urn:metanorma:doc-part:_cb905e73-049d-d60e-abaa-0ba8e4ae12d6"
                        },
                        "content": [
                          {
                            "text": "018",
                            "type": "text"
                          }
                        ],
                        "type": "paragraph"
                      }
                    ],
                    "type": "table_cell"
                  },
                  {
                    "attrs": {
                      "background": null,
                      "colspan": null,
                      "colwidth": null,
                      "rowspan": null
                    },
                    "content": [
                      {
                        "attrs": {
                          "resourceID": "urn:metanorma:doc-part:_08eb922f-b0c1-7d8b-6709-a7cf65b5f354"
                        },
                        "content": [
                          {
                            "text": "LidarSLAM計測の測量成果",
                            "type": "text"
                          }
                        ],
                        "type": "paragraph"
                      }
                    ],
                    "type": "table_cell"
                  }
                ],
                "type": "table_row"
              },
              {
                "content": [
                  {
                    "attrs": {
                      "background": null,
                      "colspan": null,
                      "colwidth": null,
                      "rowspan": null
                    },
                    "content": [
                      {
                        "attrs": {
                          "resourceID": "urn:metanorma:doc-part:_6c256899-3658-adab-eaed-8ea3e8506151"
                        },
                        "content": [
                          {
                            "text": "019",
                            "type": "text"
                          }
                        ],
                        "type": "paragraph"
                      }
                    ],
                    "type": "table_cell"
                  },
                  {
                    "attrs": {
                      "background": null,
                      "colspan": null,
                      "colwidth": null,
                      "rowspan": null
                    },
                    "content": [
                      {
                        "attrs": {
                          "resourceID": "urn:metanorma:doc-part:_8c27b1cc-e719-e861-7eae-b3a55e695a88"
                        },
                        "content": [
                          {
                            "text": "高密度航空レーザ測量の測量成果",
                            "type": "text"
                          }
                        ],
                        "type": "paragraph"
                      }
                    ],
                    "type": "table_cell"
                  }
                ],
                "type": "table_row"
              },
              {
                "content": [
                  {
                    "attrs": {
                      "background": null,
                      "colspan": null,
                      "colwidth": null,
                      "rowspan": null
                    },
                    "content": [
                      {
                        "attrs": {
                          "resourceID": "urn:metanorma:doc-part:_112edef0-bd03-d1e4-ce7d-32abd732b486"
                        },
                        "content": [
                          {
                            "text": "020",
                            "type": "text"
                          }
                        ],
                        "type": "paragraph"
                      }
                    ],
                    "type": "table_cell"
                  },
                  {
                    "attrs": {
                      "background": null,
                      "colspan": null,
                      "colwidth": null,
                      "rowspan": null
                    },
                    "content": [
                      {
                        "attrs": {
                          "resourceID": "urn:metanorma:doc-part:_5e041054-dade-9fd9-4d6c-6a749e78aa76"
                        },
                        "content": [
                          {
                            "text": "写真点群測量の測量成果",
                            "type": "text"
                          }
                        ],
                        "type": "paragraph"
                      }
                    ],
                    "type": "table_cell"
                  }
                ],
                "type": "table_row"
              },
              {
                "content": [
                  {
                    "attrs": {
                      "background": null,
                      "colspan": null,
                      "colwidth": null,
                      "rowspan": null
                    },
                    "content": [
                      {
                        "attrs": {
                          "resourceID": "urn:metanorma:doc-part:_1a4967b3-ed15-7249-0ed3-31946278a5b3"
                        },
                        "content": [
                          {
                            "text": "021",
                            "type": "text"
                          }
                        ],
                        "type": "paragraph"
                      }
                    ],
                    "type": "table_cell"
                  },
                  {
                    "attrs": {
                      "background": null,
                      "colspan": null,
                      "colwidth": null,
                      "rowspan": null
                    },
                    "content": [
                      {
                        "attrs": {
                          "resourceID": "urn:metanorma:doc-part:_f91a1c2e-2660-c26a-06d2-6f89ea5bee9c"
                        },
                        "content": [
                          {
                            "text": "三次元数値図化の測量成果",
                            "type": "text"
                          }
                        ],
                        "type": "paragraph"
                      }
                    ],
                    "type": "table_cell"
                  }
                ],
                "type": "table_row"
              },
              {
                "content": [
                  {
                    "attrs": {
                      "background": null,
                      "colspan": null,
                      "colwidth": null,
                      "rowspan": null
                    },
                    "content": [
                      {
                        "attrs": {
                          "resourceID": "urn:metanorma:doc-part:_ef1cc42a-bd1b-b072-3eff-e6e6de54bf8f"
                        },
                        "content": [
                          {
                            "text": "022",
                            "type": "text"
                          }
                        ],
                        "type": "paragraph"
                      }
                    ],
                    "type": "table_cell"
                  },
                  {
                    "attrs": {
                      "background": null,
                      "colspan": null,
                      "colwidth": null,
                      "rowspan": null
                    },
                    "content": [
                      {
                        "attrs": {
                          "resourceID": "urn:metanorma:doc-part:_90a57539-e8a5-c7f4-1fab-50f4c90082c9"
                        },
                        "content": [
                          {
                            "text": "基盤地図情報",
                            "type": "text"
                          }
                        ],
                        "type": "paragraph"
                      }
                    ],
                    "type": "table_cell"
                  }
                ],
                "type": "table_row"
              },
              {
                "content": [
                  {
                    "attrs": {
                      "background": null,
                      "colspan": null,
                      "colwidth": null,
                      "rowspan": null
                    },
                    "content": [
                      {
                        "attrs": {
                          "resourceID": "urn:metanorma:doc-part:_d743b383-748e-61b2-87e2-6c8d641b9ca4"
                        },
                        "content": [
                          {
                            "text": "023",
                            "type": "text"
                          }
                        ],
                        "type": "paragraph"
                      }
                    ],
                    "type": "table_cell"
                  },
                  {
                    "attrs": {
                      "background": null,
                      "colspan": null,
                      "colwidth": null,
                      "rowspan": null
                    },
                    "content": [
                      {
                        "attrs": {
                          "resourceID": "urn:metanorma:doc-part:_6f5b4b9e-bedb-bc87-1381-dac84f7b515f"
                        },
                        "content": [
                          {
                            "text": "数値地形図データ",
                            "type": "text"
                          }
                        ],
                        "type": "paragraph"
                      }
                    ],
                    "type": "table_cell"
                  }
                ],
                "type": "table_row"
              },
              {
                "content": [
                  {
                    "attrs": {
                      "background": null,
                      "colspan": "2",
                      "colwidth": null,
                      "rowspan": null
                    },
                    "content": [
                      {
                        "attrs": {
                          "resourceID": ""
                        },
                        "content": [
                          {
                            "text": "出典: ",
                            "type": "text"
                          },
                          {
                            "attrs": {
                              "href": "https://www.gsi.go.jp/gijyutukanri/gijyutukanri41018.html"
                            },
                            "content": [
                              {
                                "text": "作業規程の準則について",
                                "type": "text"
                              }
                            ],
                            "type": "external_link"
                          },
                          {
                            "text": "; ",
                            "type": "text"
                          },
                          {
                            "attrs": {
                              "href": "https://www.mlit.go.jp/plateau/libraries/handbooks/"
                            },
                            "content": [
                              {
                                "text": "PLATEAU Handbook #10",
                                "type": "text"
                              }
                            ],
                            "type": "external_link"
                          }
                        ],
                        "type": "paragraph"
                      }
                    ],
                    "type": "table_cell"
                  }
                ],
                "type": "table_row"
              }
            ],
            "type": "table"
          }
        ],
        "type": "tableFigure"
      }
    }
  ]
}
