{
  "title": "2.5  拡張製品仕様書の作成",
  "path": "/plateaudocument02/toc1/toc1_05",
  "content": [
    {
      "type": "title",
      "content": {
        "content": [
          {
            "text": "2.5\t拡張製品仕様書の作成",
            "type": "text"
          }
        ],
        "type": "title"
      }
    },
    {
      "type": "paragraph",
      "content": {
        "attrs": {
          "resourceID": "urn:metanorma:doc-part:_2b18cd68-cc8d-3174-02f5-859947701128"
        },
        "content": [
          {
            "attrs": {
              "resourceID": "urn:metanorma:doc-part:_e75bcb1a-4426-4938-9540-a10091220bdd"
            },
            "type": "anchor"
          },
          {
            "text": "前項までにおいて、各都市のユースケースに必要な情報について、標準製品仕様書の定義をそのまま適用する地物型等や、標準製品仕様書では不足するため新たに追加した地物型等を決定した。本項ではこれらを取りまとめ、拡張製品仕様書を作成する手順を示す。",
            "type": "text"
          }
        ],
        "type": "paragraph"
      }
    },
    {
      "type": "paragraph",
      "content": {
        "attrs": {
          "resourceID": "urn:metanorma:doc-part:_c3354c9f-b1e9-8bcb-6ad8-f5b2f5cf4768"
        },
        "content": [
          {
            "text": "なお、3D都市モデル",
            "type": "text"
          },
          {
            "attrs": {
              "resourceID": "urn:metanorma:doc-part:_9127dbef-7b5d-47a4-8426-24c714e41320"
            },
            "type": "anchor"
          },
          {
            "text": "の製品仕様書として、データ製品が作成された日付や空間的な範囲、問合せ先等を示す必要があるため、",
            "type": "text"
          },
          {
            "content": [
              {
                "text": "地物型等の拡張が無い場合も、3D都市モデルごとの拡張製品仕様書を作成する",
                "type": "text"
              }
            ],
            "type": "underline"
          },
          {
            "text": "ことになる。",
            "type": "text"
          }
        ],
        "type": "paragraph"
      }
    }
  ]
}
