{
  "title": "N.3.1.3.1  原典資料",
  "path": "/plateaudocument02/tocN/tocN_03/幾何オブジェクトの作成__9/_lod2_15/原典資料__49",
  "content": [
    {
      "type": "title",
      "content": {
        "content": [
          {
            "text": "N.3.1.3.1\t原典資料",
            "type": "text"
          }
        ],
        "type": "title"
      }
    },
    {
      "type": "tableFigure",
      "content": {
        "attrs": {
          "resourceID": "urn:metanorma:doc-part:tab-N-6"
        },
        "content": [
          {
            "content": [
              {
                "content": [
                  {
                    "text": "表",
                    "type": "text"
                  }
                ],
                "type": "span"
              },
              {
                "text": "N-11 — LOD2の原典資料",
                "type": "text"
              }
            ],
            "type": "figCaption"
          },
          {
            "attrs": {
              "colWidths": []
            },
            "content": [
              {
                "content": [
                  {
                    "attrs": {
                      "background": null,
                      "colspan": null,
                      "colwidth": null,
                      "rowspan": null
                    },
                    "type": "table_header"
                  },
                  {
                    "attrs": {
                      "background": null,
                      "colspan": null,
                      "colwidth": null,
                      "rowspan": null
                    },
                    "content": [
                      {
                        "attrs": {
                          "resourceID": ""
                        },
                        "content": [
                          {
                            "text": "水平位置",
                            "type": "text"
                          }
                        ],
                        "type": "paragraph"
                      }
                    ],
                    "type": "table_header"
                  },
                  {
                    "attrs": {
                      "background": null,
                      "colspan": null,
                      "colwidth": null,
                      "rowspan": null
                    },
                    "content": [
                      {
                        "attrs": {
                          "resourceID": ""
                        },
                        "content": [
                          {
                            "text": "高さ",
                            "type": "text"
                          }
                        ],
                        "type": "paragraph"
                      }
                    ],
                    "type": "table_header"
                  },
                  {
                    "attrs": {
                      "background": null,
                      "colspan": null,
                      "colwidth": null,
                      "rowspan": null
                    },
                    "content": [
                      {
                        "attrs": {
                          "resourceID": ""
                        },
                        "content": [
                          {
                            "text": "上面の形状",
                            "type": "text"
                          }
                        ],
                        "type": "paragraph"
                      }
                    ],
                    "type": "table_header"
                  },
                  {
                    "attrs": {
                      "background": null,
                      "colspan": null,
                      "colwidth": null,
                      "rowspan": null
                    },
                    "content": [
                      {
                        "attrs": {
                          "resourceID": ""
                        },
                        "content": [
                          {
                            "text": "側面の形状",
                            "type": "text"
                          }
                        ],
                        "type": "paragraph"
                      }
                    ],
                    "type": "table_header"
                  },
                  {
                    "attrs": {
                      "background": null,
                      "colspan": null,
                      "colwidth": null,
                      "rowspan": null
                    },
                    "content": [
                      {
                        "attrs": {
                          "resourceID": ""
                        },
                        "content": [
                          {
                            "text": "付属物等",
                            "type": "text"
                          }
                        ],
                        "type": "paragraph"
                      }
                    ],
                    "type": "table_header"
                  }
                ],
                "type": "table_row"
              },
              {
                "content": [
                  {
                    "attrs": {
                      "background": null,
                      "colspan": null,
                      "colwidth": null,
                      "rowspan": null
                    },
                    "content": [
                      {
                        "attrs": {
                          "resourceID": ""
                        },
                        "content": [
                          {
                            "text": "LOD2",
                            "type": "text"
                          }
                        ],
                        "type": "paragraph"
                      }
                    ],
                    "type": "table_header"
                  },
                  {
                    "attrs": {
                      "background": null,
                      "colspan": null,
                      "colwidth": null,
                      "rowspan": null
                    },
                    "content": [
                      {
                        "attrs": {
                          "resourceID": "urn:metanorma:doc-part:_7c219f3e-0ab9-a942-aa86-c3ee2aa21991"
                        },
                        "content": [
                          {
                            "text": "以下のいずれかのデータを一つ以上使用する",
                            "type": "text"
                          }
                        ],
                        "type": "paragraph"
                      },
                      {
                        "content": [
                          {
                            "content": [
                              {
                                "attrs": {
                                  "resourceID": "urn:metanorma:doc-part:_ac8919d0-b260-da86-5794-94dece5658cf"
                                },
                                "content": [
                                  {
                                    "text": "都市計画図等のDMデータ",
                                    "type": "text"
                                  }
                                ],
                                "type": "paragraph"
                              }
                            ],
                            "type": "list_item"
                          },
                          {
                            "content": [
                              {
                                "attrs": {
                                  "resourceID": "urn:metanorma:doc-part:_5cbac2ee-33f2-dde3-c7c6-a58196382a8a"
                                },
                                "content": [
                                  {
                                    "text": "平面図",
                                    "type": "text"
                                  }
                                ],
                                "type": "paragraph"
                              }
                            ],
                            "type": "list_item"
                          },
                          {
                            "content": [
                              {
                                "attrs": {
                                  "resourceID": "urn:metanorma:doc-part:_b227bc72-a2de-009c-ee41-752b7a48728d"
                                },
                                "content": [
                                  {
                                    "text": "航空写真",
                                    "type": "text"
                                  }
                                ],
                                "type": "paragraph"
                              }
                            ],
                            "type": "list_item"
                          }
                        ],
                        "type": "bullet_list"
                      }
                    ],
                    "type": "table_cell"
                  },
                  {
                    "attrs": {
                      "background": null,
                      "colspan": null,
                      "colwidth": null,
                      "rowspan": null
                    },
                    "content": [
                      {
                        "attrs": {
                          "resourceID": "urn:metanorma:doc-part:_cc593ba4-f9da-ed16-7591-2d0ddc5bf7f0"
                        },
                        "content": [
                          {
                            "text": "以下のいずれかのデータを一つ以上使用する",
                            "type": "text"
                          }
                        ],
                        "type": "paragraph"
                      },
                      {
                        "content": [
                          {
                            "content": [
                              {
                                "attrs": {
                                  "resourceID": "urn:metanorma:doc-part:_62e9f82f-9fdb-24c0-1d5e-f6e9f097eb54"
                                },
                                "content": [
                                  {
                                    "text": "断面図又は構造図等",
                                    "type": "text"
                                  }
                                ],
                                "type": "paragraph"
                              }
                            ],
                            "type": "list_item"
                          },
                          {
                            "content": [
                              {
                                "attrs": {
                                  "resourceID": "urn:metanorma:doc-part:_e1fd3893-4c3e-5816-9da8-ecad4a41daa7"
                                },
                                "content": [
                                  {
                                    "text": "航空レーザ点群",
                                    "type": "text"
                                  }
                                ],
                                "type": "paragraph"
                              }
                            ],
                            "type": "list_item"
                          },
                          {
                            "content": [
                              {
                                "attrs": {
                                  "resourceID": "urn:metanorma:doc-part:_fdedd75b-766a-0c9f-d0e4-e47844239e4f"
                                },
                                "content": [
                                  {
                                    "text": "航空写真から作成した点群",
                                    "type": "text"
                                  }
                                ],
                                "type": "paragraph"
                              }
                            ],
                            "type": "list_item"
                          }
                        ],
                        "type": "bullet_list"
                      }
                    ],
                    "type": "table_cell"
                  },
                  {
                    "attrs": {
                      "background": null,
                      "colspan": null,
                      "colwidth": null,
                      "rowspan": null
                    },
                    "content": [
                      {
                        "attrs": {
                          "resourceID": "urn:metanorma:doc-part:_500fd852-dc66-ed4c-f31b-233a0b809b65"
                        },
                        "content": [
                          {
                            "text": "以下のいずれかのデータを一つ以上使用する",
                            "type": "text"
                          }
                        ],
                        "type": "paragraph"
                      },
                      {
                        "content": [
                          {
                            "content": [
                              {
                                "attrs": {
                                  "resourceID": "urn:metanorma:doc-part:_c38c35a0-44ea-92db-9326-a5a775329d8d"
                                },
                                "content": [
                                  {
                                    "text": "平面図及び断面図又は構造図等",
                                    "type": "text"
                                  }
                                ],
                                "type": "paragraph"
                              }
                            ],
                            "type": "list_item"
                          },
                          {
                            "content": [
                              {
                                "attrs": {
                                  "resourceID": "urn:metanorma:doc-part:_472a1b52-8c0c-e320-22e5-ead586d5a2e0"
                                },
                                "content": [
                                  {
                                    "text": "航空レーザ点群",
                                    "type": "text"
                                  }
                                ],
                                "type": "paragraph"
                              }
                            ],
                            "type": "list_item"
                          },
                          {
                            "content": [
                              {
                                "attrs": {
                                  "resourceID": "urn:metanorma:doc-part:_33d7524b-44f9-6f31-5e8b-30d14324c525"
                                },
                                "content": [
                                  {
                                    "text": "航空写真から作成した点群",
                                    "type": "text"
                                  }
                                ],
                                "type": "paragraph"
                              }
                            ],
                            "type": "list_item"
                          }
                        ],
                        "type": "bullet_list"
                      }
                    ],
                    "type": "table_cell"
                  },
                  {
                    "attrs": {
                      "background": null,
                      "colspan": null,
                      "colwidth": null,
                      "rowspan": null
                    },
                    "content": [
                      {
                        "attrs": {
                          "resourceID": "urn:metanorma:doc-part:_a82005bf-ba85-93d3-b740-21887084e70d"
                        },
                        "content": [
                          {
                            "text": "―",
                            "type": "text"
                          }
                        ],
                        "type": "paragraph"
                      }
                    ],
                    "type": "table_cell"
                  },
                  {
                    "attrs": {
                      "background": null,
                      "colspan": null,
                      "colwidth": null,
                      "rowspan": null
                    },
                    "content": [
                      {
                        "attrs": {
                          "resourceID": "urn:metanorma:doc-part:_066a0207-306f-522c-27e4-bea3a7724081"
                        },
                        "content": [
                          {
                            "text": "―",
                            "type": "text"
                          }
                        ],
                        "type": "paragraph"
                      }
                    ],
                    "type": "table_cell"
                  }
                ],
                "type": "table_row"
              }
            ],
            "type": "table"
          }
        ],
        "type": "tableFigure"
      }
    }
  ]
}
